jdhp
